cubo/__init__.py
cubo/cubo.py
cubo/utils.py
cubo_numpy2_0-2026.1.0.dist-info/licenses/LICENSE
docs/conf.py
test/test_cubo.py
cubo_numpy2_0-2026.1.0.dist-info/METADATA
cubo_numpy2_0-2026.1.0.dist-info/WHEEL
cubo_numpy2_0-2026.1.0.dist-info/top_level.txt
cubo_numpy2_0-2026.1.0.dist-info/RECORD
