Metadata-Version: 2.4
Name: Cubo-Numpy2.0
Version: 2026.1.0
Summary: On-Demand Earth System Data Cubes in Python
Author-email: David Montero Loaiza <dml.mont@gmail.com>, Louis Ferdinand Trinkle <louis.trinkle@gmail.com>
License: MIT
Project-URL: Homepage, https://github.com/davemlz/cubo
Project-URL: Documentation, https://cubo.readthedocs.io/
Project-URL: Repository, https://github.com/davemlz/cubo
Classifier: Development Status :: 2 - Pre-Alpha
Classifier: License :: OSI Approved :: MIT License
Classifier: Programming Language :: Python
Classifier: Programming Language :: Python :: 3
Classifier: Programming Language :: Python :: 3.10
Classifier: Programming Language :: Python :: 3.11
Classifier: Programming Language :: Python :: 3.12
Classifier: Programming Language :: Python :: 3.13
Classifier: Programming Language :: Python :: 3.14
Requires-Python: >=3.10
License-File: LICENSE
Requires-Dist: dask>=2026.1.1
Requires-Dist: numpy>=2.2.6
Requires-Dist: pandas>=2.3.3
Requires-Dist: planetary_computer>=1.0.0
Requires-Dist: pystac_client>=0.9.0
Requires-Dist: scipy>=1.15.3
Requires-Dist: stackstac>=0.5.1
Requires-Dist: xarray>=2025.6.1
Provides-Extra: ee
Requires-Dist: xee>=0.0.24; extra == "ee"
Dynamic: license-file
